pbi2snow/__init__.py
pbi2snow/cli.py
pbi2snow/extract.py
pbi2snow/sqlgen.py
pbi2snow/translator.py
pbi2snow-2.0.0.dist-info/licenses/LICENSE
pbi2snow-2.0.0.dist-info/METADATA
pbi2snow-2.0.0.dist-info/WHEEL
pbi2snow-2.0.0.dist-info/entry_points.txt
pbi2snow-2.0.0.dist-info/top_level.txt
pbi2snow-2.0.0.dist-info/RECORD
