Metadata-Version: 2.4
Name: pbi2snow
Version: 2.0.0
Summary: Power BI to Snowflake SQL translator with enhanced M and DAX support
Author-email: LLMs Research team <dip@llmsresearch.com>
License: MIT
Project-URL: Homepage, https://github.com/llmsresearch/pbi2snow
Project-URL: Documentation, https://github.com/llmsresearch/pbi2snow#readme
Project-URL: Repository, https://github.com/llmsresearch/pbi2snow.git
Project-URL: Bug Tracker, https://github.com/llmsresearch/pbi2snow/issues
Keywords: powerbi,snowflake,sql,translator,m-language,dax
Classifier: Development Status :: 4 - Beta
Classifier: Intended Audience :: Developers
Classifier: Topic :: Database
Classifier: Topic :: Software Development :: Code Generators
Classifier: License :: OSI Approved :: MIT License
Classifier: Programming Language :: Python :: 3
Classifier: Programming Language :: Python :: 3.8
Classifier: Programming Language :: Python :: 3.9
Classifier: Programming Language :: Python :: 3.10
Classifier: Programming Language :: Python :: 3.11
Requires-Python: >=3.8
License-File: LICENSE
Requires-Dist: click>=8.0
Requires-Dist: jinja2>=3.0
Requires-Dist: pyyaml>=6.0
Provides-Extra: dev
Requires-Dist: pytest>=7.0; extra == "dev"
Requires-Dist: pytest-cov>=4.0; extra == "dev"
Requires-Dist: black>=22.0; extra == "dev"
Requires-Dist: flake8>=5.0; extra == "dev"
Requires-Dist: mypy>=0.990; extra == "dev"
Dynamic: license-file
